sarya/UI.py
sarya/__init__.py
sarya/client.py
sarya/configuration.py
sarya/typings.py
sarya-0.0.3.3.dist-info/LICENSE
sarya-0.0.3.3.dist-info/METADATA
sarya-0.0.3.3.dist-info/WHEEL
sarya-0.0.3.3.dist-info/RECORD
